django_highlander-0.0.1.dev0.dist-info/DESCRIPTION.rst
django_highlander-0.0.1.dev0.dist-info/METADATA
django_highlander-0.0.1.dev0.dist-info/RECORD
django_highlander-0.0.1.dev0.dist-info/WHEEL
django_highlander-0.0.1.dev0.dist-info/metadata.json
django_highlander-0.0.1.dev0.dist-info/top_level.txt
djangohighlander/__init__.py
djangohighlander/command.py
