Metadata-Version: 2.0
Name: django-highlander
Version: 0.0.1.dev0
Summary: Django management Command that prevents simultaneous instances
Home-page: https://github.com/scardine/django-highlander
Author: Paulo Scardine
Author-email: paulos@xtend.com.br
License: MIT
Platform: UNKNOWN
Requires-Dist: django
Requires-Dist: tendo
